datalake_ingestion/__init__.py
datalake_ingestion/collect.py
datalake_ingestion/exceptions.py
datalake_ingestion/preprocess.py
datalake_ingestion/schemas/collect.json
datalake_ingestion-1.0.2.dist-info/LICENSE
datalake_ingestion-1.0.2.dist-info/WHEEL
datalake_ingestion-1.0.2.dist-info/METADATA
datalake_ingestion-1.0.2.dist-info/RECORD
