Metadata-Version: 2.1
Name: datalake-ingestion
Version: 1.0.2
Summary: Datalake ingestion workflow
Home-page: https://github.com/equancy/datalake-ingestion
License: MIT
Author: Didier SCHMITT
Author-email: dschmitt@equancy.com
Requires-Python: >=3.8,<4.0
Classifier: Development Status :: 4 - Beta
Classifier: License :: OSI Approved :: MIT License
Classifier: Programming Language :: Python :: 3
Classifier: Programming Language :: Python :: 3.10
Classifier: Programming Language :: Python :: 3.8
Classifier: Programming Language :: Python :: 3.9
Classifier: Topic :: Software Development :: Libraries :: Python Modules
Requires-Dist: PyYAML (>=6.0,<7.0)
Requires-Dist: datalake-framework (>=1.0.0,<2.0.0)
Requires-Dist: jsonschema (>=4.2.1,<5.0.0)
Requires-Dist: pendulum (>=2.1.2,<3.0.0)
Project-URL: Documentation, https://docs.equancy.cloud/datalake-ingestion/latest/index.html
Project-URL: Repository, https://github.com/equancy/datalake-ingestion
